archie/__init__.py
archie/backup.py
archie/configuration.py
archie/helpers.py
archie/handlers/__init__.py
archie/handlers/install.py
archie/handlers/restore.py
archie-0.0.4.data/scripts/arc
archie-0.0.4.dist-info/LICENSE.txt
archie-0.0.4.dist-info/METADATA
archie-0.0.4.dist-info/WHEEL
archie-0.0.4.dist-info/top_level.txt
archie-0.0.4.dist-info/RECORD
