Metadata-Version: 2.1
Name: archie
Version: 0.0.4
Summary: Symlink management for configuration (rc) file.
Home-page: http://bitbucket.org/fudanchii/archie
Author: Nurahmadie
Author-email: nurahmadie@gmail.com
Classifier: Development Status :: 3 - Alpha
Classifier: Environment :: Console
Classifier: Intended Audience :: System Administrators
Classifier: Intended Audience :: Developers
Classifier: License :: OSI Approved :: MIT License
Classifier: Operating System :: POSIX
Classifier: Programming Language :: Python
License-File: LICENSE.txt
Requires-Dist: docopt
